{
  "main": {
    "id": "beb07e6320d3c5e1",
    "type": "split",
    "children": [
      {
        "id": "11fe3bc71ce8b54f",
        "type": "tabs",
        "children": [
          {
            "id": "e82d489278adfefc",
            "type": "leaf",
            "state": {
              "type": "markdown",
              "state": {
                "file": "Oracle/무제 파일.md",
                "mode": "source",
                "source": false
              }
            }
          },
          {
            "id": "a6087407eafa4fb6",
            "type": "leaf",
            "state": {
              "type": "markdown",
              "state": {
                "file": "Java/MyBatis.md",
                "mode": "source",
                "source": false
              }
            }
          }
        ],
        "currentTab": 1
      }
    ],
    "direction": "vertical"
  },
  "left": {
    "id": "e027ca349f2ec27d",
    "type": "split",
    "children": [
      {
        "id": "b9c926b518af74fa",
        "type": "tabs",
        "children": [
          {
            "id": "4745c162c97bae2b",
            "type": "leaf",
            "state": {
              "type": "file-explorer",
              "state": {
                "sortOrder": "alphabetical"
              }
            }
          },
          {
            "id": "45f04dadb60bea45",
            "type": "leaf",
            "state": {
              "type": "search",
              "state": {
                "query": "tag:#ㄹㅇㄹㅇ",
                "matchingCase": false,
                "explainSearch": false,
                "collapseAll": false,
                "extraContext": false,
                "sortOrder": "alphabetical"
              }
            }
          },
          {
            "id": "c12d15b8074664db",
            "type": "leaf",
            "state": {
              "type": "bookmarks",
              "state": {}
            }
          }
        ]
      }
    ],
    "direction": "horizontal",
    "width": 274.5
  },
  "right": {
    "id": "31b68a82de377f79",
    "type": "split",
    "children": [
      {
        "id": "e0ed5c2f655b3280",
        "type": "tabs",
        "children": [
          {
            "id": "243971927a9706c0",
            "type": "leaf",
            "state": {
              "type": "backlink",
              "state": {
                "file": "Java/MyBatis.md",
                "collapseAll": false,
                "extraContext": false,
                "sortOrder": "alphabetical",
                "showSearch": false,
                "searchQuery": "",
                "backlinkCollapsed": false,
                "unlinkedCollapsed": true
              }
            }
          },
          {
            "id": "54adcdcf0386278e",
            "type": "leaf",
            "state": {
              "type": "outgoing-link",
              "state": {
                "file": "Java/MyBatis.md",
                "linksCollapsed": false,
                "unlinkedCollapsed": true
              }
            }
          },
          {
            "id": "93cb206bc717169a",
            "type": "leaf",
            "state": {
              "type": "tag",
              "state": {
                "sortOrder": "frequency",
                "useHierarchy": true
              }
            }
          },
          {
            "id": "96bdb638d1ce7df0",
            "type": "leaf",
            "state": {
              "type": "outline",
              "state": {
                "file": "Java/MyBatis.md"
              }
            }
          }
        ]
      }
    ],
    "direction": "horizontal",
    "width": 200,
    "collapsed": true
  },
  "left-ribbon": {
    "hiddenItems": {
      "switcher:퀵 스위처 열기": false,
      "graph:그래프 뷰 열기": false,
      "canvas:새 캔버스 만들기": false,
      "daily-notes:오늘의 데일리 노트 열기": false,
      "templates:템플릿 삽입": false,
      "command-palette:명령어 팔레트 열기": false,
      "obsidian-excalidraw-plugin:Create new drawing": false
    }
  },
  "active": "a6087407eafa4fb6",
  "lastOpenFiles": [
    "기타파일/옵시디언 사용법.md",
    "Oracle/무제 파일.md",
    "임베딩.md",
    "Excalidraw/Drawing 2024-01-18 16.06.43.excalidraw.md",
    "Java/MyBatis.md",
    "Oracle",
    "Pasted image 20240118173828.png",
    "Pasted image 20240118143436.png",
    "Excalidraw/Drawing 2024-01-18 14.30.12.excalidraw.md",
    "Excalidraw/Drawing 2024-01-18 14.42.37_0.excalidraw.md",
    "Excalidraw/Drawing 2024-01-18 14.42.37.excalidraw.md",
    "무제 폴더/Drawing 2024-01-18 14.42.36.excalidraw.md",
    "Pasted image 20240118143431.png",
    "Excalidraw",
    "Java",
    "문서링크.md",
    "무제 파일 1.md",
    "Excalidraw/Drawing 2024-01-18 14.11.50.excalidraw.md",
    "기타파일/Fonts/나눔손글씨 성실체.ttf",
    "기타파일/Fonts",
    "무제 파일.canvas",
    "무제 폴더/무제 파일.canvas",
    "기타파일",
    "README.md"
  ]
}